{
	"collectionName": "components_teaser_manuals",
	"info": {
		"displayName": "Handmatig Teaser invullen",
		"icon": "pin",
		"description": ""
	},
	"options": {},
	"attributes": {
		"title": {
			"type": "string",
			"required": true
		},
		"text": {
			"type": "text"
		},
		"image": {
			"type": "media",
			"multiple": false,
			"required": false,
			"allowedTypes": ["images", "files", "videos", "audios"]
		},
		"button": {
			"type": "component",
			"repeatable": false,
			"required": false,
			"component": "input.button"
		}
	}
}
